geohash_polygon.libs/libgcc_s-0366c7ba.so.1
geohash_polygon/__init__.py
geohash_polygon/geohash_polygon.abi3.so
rusty_polygon_geohasher-0.3.0.dist-info/METADATA
rusty_polygon_geohasher-0.3.0.dist-info/WHEEL
rusty_polygon_geohasher-0.3.0.dist-info/RECORD
