Metadata-Version: 2.4
Name: rusty-polygon-geohasher
Version: 0.3.0
Keywords: polygon,geohashes,geospatial
Home-Page: https://github.com/nexmoov/rusty-polygon-geohasher
Author: Francois Maillet <francois@locallogic.co>
Author-email: Francois Maillet <francois@locallogic.co>
License: MIT
